ml_collections/AUTHORS
ml_collections/__init__.py
ml_collections/conftest.py
ml_collections/config_dict/__init__.py
ml_collections/config_dict/config_dict.py
ml_collections/config_dict/examples/config.py
ml_collections/config_dict/examples/config_dict_advanced.py
ml_collections/config_dict/examples/config_dict_basic.py
ml_collections/config_dict/examples/config_dict_initialization.py
ml_collections/config_dict/examples/config_dict_lock.py
ml_collections/config_dict/examples/config_dict_placeholder.py
ml_collections/config_dict/examples/field_reference.py
ml_collections/config_dict/examples/frozen_config_dict.py
ml_collections/config_flags/__init__.py
ml_collections/config_flags/config_flags.py
ml_collections/config_flags/config_path.py
ml_collections/config_flags/tuple_parser.py
ml_collections/config_flags/examples/config.py
ml_collections/config_flags/examples/define_config_dataclass_basic.py
ml_collections/config_flags/examples/define_config_dict_basic.py
ml_collections/config_flags/examples/define_config_file_basic.py
ml_collections/config_flags/examples/parameterised_config.py
ml_collections/config_flags/tests/configdict_config.py
ml_collections/config_flags/tests/fieldreference_config.py
ml_collections/config_flags/tests/ioerror_config.py
ml_collections/config_flags/tests/literal_config.py
ml_collections/config_flags/tests/mini_config.py
ml_collections/config_flags/tests/mock_config.py
ml_collections/config_flags/tests/parameterised_config.py
ml_collections/config_flags/tests/spork.py
ml_collections/config_flags/tests/typeerror_config.py
ml_collections/config_flags/tests/valueerror_config.py
ml_collections-1.0.0.dist-info/LICENSE
ml_collections-1.0.0.dist-info/WHEEL
ml_collections-1.0.0.dist-info/METADATA
ml_collections-1.0.0.dist-info/RECORD
