Metadata-Version: 2.3
Name: ml_collections
Version: 1.0.0
Summary: ML Collections is a library of Python collections designed for ML usecases.
Keywords: 
Author-email: ML Collections Authors <ml-collections@google.com>
Requires-Python: >=3.10
Classifier: Development Status :: 4 - Beta
Classifier: Intended Audience :: Developers
Classifier: Intended Audience :: Science/Research
Classifier: License :: OSI Approved :: Apache Software License
Classifier: Programming Language :: Python
Classifier: Topic :: Scientific/Engineering
Classifier: Topic :: Scientific/Engineering :: Artificial Intelligence
Classifier: Topic :: Software Development :: Libraries
Classifier: Topic :: Software Development :: Libraries :: Python Modules
Requires-Dist: absl-py
Requires-Dist: six
Requires-Dist: PyYAML
Requires-Dist: pytest ; extra == "dev"
Requires-Dist: pytest-xdist ; extra == "dev"
Requires-Dist: pylint>=2.6.0 ; extra == "dev"
Requires-Dist: pyink ; extra == "dev"
Project-URL: documentation, https://ml-collections.readthedocs.io
Project-URL: homepage, https://github.com/google/ml_collections
Project-URL: repository, https://github.com/google/ml_collections
Provides-Extra: dev
